geosuite/__init__.py
geosuite/analysis/__init__.py
geosuite/analysis/ts2net_integration.py
geosuite/cli/__init__.py
geosuite/cli/analyze.py
geosuite/cli/batch_process.py
geosuite/cli/workflow.py
geosuite/config/__init__.py
geosuite/config/manager.py
geosuite/data/__init__.py
geosuite/data/demo_datasets.py
geosuite/data/files/demo_facies.parquet
geosuite/data/files/demo_well_logs.parquet
geosuite/data/files/facies_vectors.parquet
geosuite/data/files/field_data.parquet
geosuite/data/files/nofacies_data.parquet
geosuite/data/files/training_data.parquet
geosuite/data/files/validation_data_nofacies.parquet
geosuite/data/files/well_data_with_facies.parquet
geosuite/data/files/KSdata/test_wells.parquet
geosuite/data/files/KSdata/training_wells.parquet
geosuite/forecasting/__init__.py
geosuite/forecasting/bayesian_decline.py
geosuite/forecasting/decline_models.py
geosuite/forecasting/decomposition.py
geosuite/forecasting/monte_carlo_forecast.py
geosuite/forecasting/production_analysis.py
geosuite/forecasting/scenario_forecasting.py
geosuite/forecasting/validation.py
geosuite/geomech/__init__.py
geosuite/geomech/basic.py
geosuite/geomech/failure_criteria.py
geosuite/geomech/fracture_orientation.py
geosuite/geomech/parallel.py
geosuite/geomech/pressures.py
geosuite/geomech/profiles.py
geosuite/geomech/stress_inversion.py
geosuite/geomech/stress_polygon.py
geosuite/geomech/stresses.py
geosuite/geospatial/__init__.py
geosuite/imaging/__init__.py
geosuite/imaging/core_processing.py
geosuite/io/__init__.py
geosuite/io/crs_utils.py
geosuite/io/csv_loader.py
geosuite/io/dlis_parser.py
geosuite/io/las_loader.py
geosuite/io/ppdm_parser.py
geosuite/io/remote_access.py
geosuite/io/resqml_parser.py
geosuite/io/segy_loader.py
geosuite/io/witsml_parser.py
geosuite/ml/__init__.py
geosuite/ml/classifiers.py
geosuite/ml/clustering.py
geosuite/ml/confusion_matrix_utils.py
geosuite/ml/cross_validation.py
geosuite/ml/deep_models.py
geosuite/ml/enhanced_classifiers.py
geosuite-0.1.4.dist-info/licenses/LICENSE
geosuite-0.1.4.dist-info/METADATA
geosuite-0.1.4.dist-info/WHEEL
geosuite-0.1.4.dist-info/entry_points.txt
geosuite-0.1.4.dist-info/top_level.txt
geosuite-0.1.4.dist-info/RECORD
