Metadata-Version: 2.4
Name: geosuite
Version: 0.1.4
Summary: A Python library for geoscience workflows: geomechanics, petrophysics, machine learning, and data I/O
Home-page: https://github.com/kylejones200/geosuite
Author: K. Jones
Author-email: "K. Jones" <kyletjones@gmail.com>
License: MIT
Project-URL: Homepage, https://github.com/kylejones200/geosuite
Project-URL: Documentation, https://geosuite.readthedocs.io
Project-URL: Repository, https://github.com/kylejones200/geosuite
Project-URL: Issues, https://github.com/kylejones200/geosuite/issues
Keywords: geoscience,geophysics,petrophysics,geomechanics,petroleum,well-log,machine-learning,geology
Classifier: Development Status :: 4 - Beta
Classifier: Intended Audience :: Science/Research
Classifier: Topic :: Scientific/Engineering
Classifier: Topic :: Scientific/Engineering :: Physics
Classifier: License :: OSI Approved :: MIT License
Classifier: Programming Language :: Python :: 3
Classifier: Programming Language :: Python :: 3.12
Requires-Python: >=3.12
License-File: LICENSE
Requires-Dist: pandas>=2.0
Requires-Dist: numpy>=2.0.0
Requires-Dist: scipy>=1.13.0
Requires-Dist: scikit-learn>=1.3
Requires-Dist: matplotlib>=3.7
Requires-Dist: signalplot>=0.1.0
Requires-Dist: lasio>=0.30
Requires-Dist: segyio>=1.9
Requires-Dist: ruptures>=1.1
Requires-Dist: joblib>=1.3.0
Requires-Dist: cloudpickle>=2.2.0
Requires-Dist: numba>=0.58.0
Requires-Dist: pyarrow>=14.0.0
Requires-Dist: pyyaml>=6.0
Provides-Extra: visualization
Requires-Dist: plotly>=5.0.0; extra == "visualization"
Requires-Dist: folium>=0.14.0; extra == "visualization"
Requires-Dist: geopandas>=0.14.0; extra == "visualization"
Requires-Dist: shapely>=2.0.0; extra == "visualization"
Provides-Extra: analysis
Requires-Dist: ts2net>=0.7.0; extra == "analysis"
Provides-Extra: data-formats
Requires-Dist: resqpy>=0.7.0; extra == "data-formats"
Requires-Dist: dlisio>=0.7.0; extra == "data-formats"
Requires-Dist: pyproj>=3.6.0; extra == "data-formats"
Requires-Dist: requests>=2.31.0; extra == "data-formats"
Requires-Dist: websocket-client>=1.6.0; extra == "data-formats"
Provides-Extra: forecasting
Requires-Dist: pymc>=5.0.0; extra == "forecasting"
Requires-Dist: arviz>=0.15.0; extra == "forecasting"
Provides-Extra: ml
Requires-Dist: mlflow>=2.8.0; extra == "ml"
Requires-Dist: mlflow[extras]>=2.8.0; extra == "ml"
Requires-Dist: shap>=0.44.0; extra == "ml"
Provides-Extra: deep
Requires-Dist: torch>=2.0.0; extra == "deep"
Requires-Dist: tensorflow>=2.13.0; extra == "deep"
Provides-Extra: optimization
Requires-Dist: optuna>=3.0.0; extra == "optimization"
Provides-Extra: geospatial
Requires-Dist: apache-sedona==1.5.1; extra == "geospatial"
Requires-Dist: pyspark<3.5.0,>=3.4.0; extra == "geospatial"
Requires-Dist: shapely>=2.0.0; extra == "geospatial"
Requires-Dist: pyproj>=3.6.0; extra == "geospatial"
Requires-Dist: geopandas>=0.14.0; extra == "geospatial"
Requires-Dist: h3>=4.1.0; extra == "geospatial"
Requires-Dist: fiona>=1.9.0; extra == "geospatial"
Provides-Extra: data
Requires-Dist: openpyxl>=3.1.5; extra == "data"
Requires-Dist: duckdb>=1.1.3; extra == "data"
Provides-Extra: webapp
Requires-Dist: Flask>=3.0.0; extra == "webapp"
Requires-Dist: dash>=2.16; extra == "webapp"
Requires-Dist: dash-bootstrap-components>=1.4; extra == "webapp"
Requires-Dist: dash-echarts>=0.0.7; extra == "webapp"
Requires-Dist: python-dotenv>=1.0.0; extra == "webapp"
Requires-Dist: gunicorn>=21.0.0; extra == "webapp"
Provides-Extra: imaging
Requires-Dist: scikit-image>=0.21; extra == "imaging"
Provides-Extra: modeling
Requires-Dist: pygeomodeling>=0.3.0; extra == "modeling"
Requires-Dist: pykrige>=1.6.0; extra == "modeling"
Provides-Extra: dev
Requires-Dist: pytest>=7.4.0; extra == "dev"
Requires-Dist: pytest-cov>=4.1.0; extra == "dev"
Requires-Dist: pytest-mock>=3.11.1; extra == "dev"
Requires-Dist: black>=23.0.0; extra == "dev"
Requires-Dist: ruff>=0.1.0; extra == "dev"
Requires-Dist: isort>=5.12.0; extra == "dev"
Requires-Dist: mypy>=1.0.0; extra == "dev"
Requires-Dist: types-requests; extra == "dev"
Requires-Dist: jupyter>=1.0.0; extra == "dev"
Requires-Dist: jupyterlab>=4.0.0; extra == "dev"
Requires-Dist: sphinx>=7.0.0; extra == "dev"
Requires-Dist: sphinx-rtd-theme>=2.0.0; extra == "dev"
Requires-Dist: sphinx-autobuild>=2024.0.0; extra == "dev"
Requires-Dist: myst-parser>=2.0.0; extra == "dev"
Provides-Extra: all
Requires-Dist: geosuite[data,dev,geospatial,imaging,ml,modeling,webapp]; extra == "all"
Dynamic: author
Dynamic: home-page
Dynamic: license-file
Dynamic: requires-python
